torchvision_detection/__init__.py
torchvision_detection/coco_eval.py
torchvision_detection/coco_utils.py
torchvision_detection/engine.py
torchvision_detection/transforms.py
torchvision_detection/utils.py
torchvision_detection-0.6.5.dist-info/LICENSE.md
torchvision_detection-0.6.5.dist-info/METADATA
torchvision_detection-0.6.5.dist-info/WHEEL
torchvision_detection-0.6.5.dist-info/top_level.txt
torchvision_detection-0.6.5.dist-info/RECORD
